pdsupp_cli/__init__.py
pdsupp_cli/commands.py
pdsupp_cli/py.typed
pdsupp_cli-0.1.1.dist-info/WHEEL
pdsupp_cli-0.1.1.dist-info/entry_points.txt
pdsupp_cli-0.1.1.dist-info/METADATA
pdsupp_cli-0.1.1.dist-info/RECORD
