Metadata-Version: 2.1
Name: pdsupp-cli
Version: 0.1.1
Summary: (pre-release) PagerDuty Public Support Scripts CLI App
Author: Ethan Skowronski-Lutz
Author-email: 33399972+ethanmsl@users.noreply.github.com
Requires-Python: >=3.10,<4.0
Classifier: Programming Language :: Python :: 3
Classifier: Programming Language :: Python :: 3.10
Classifier: Programming Language :: Python :: 3.11
Requires-Dist: gracy (>=1.6.0,<2.0.0)
Requires-Dist: typer[all] (>=0.7.0,<0.8.0)
